<?xml version="1.0"?>
<retorno><status>success</status><data><lancamentosRequisitados><codigoWS>1001</codigoWS><lancamentosRequisitados><dataDePrevisao>2025-01-06</dataDePrevisao><atrasosDevidoAFeriados></atrasosDevidoAFeriados><descricaoFeriados>Devido ao(s) Feriado(s) de "V&#xE9;spera de Ano-Novo (31/12/2024)" e "Confraterniza&#xE7;&#xE3;o Universal (01/01/2025)", a data de previs&#xE3;o foi adiada para 2 dia(s)</descricaoFeriados></lancamentosRequisitados></lancamentosRequisitados><lancamentosRequisitados><codigoWS>1002</codigoWS><previsao></previsao></lancamentosRequisitados></data></retorno>
